delta/__init__.py
delta/_typing.py
delta/pip_utils.py
delta/py.typed
delta/tables.py
delta/connect/__init__.py
delta/connect/_typing.py
delta/connect/exceptions.py
delta/connect/plan.py
delta/connect/tables.py
delta/connect/proto/__init__.py
delta/connect/proto/base_pb2.py
delta/connect/proto/commands_pb2.py
delta/connect/proto/relations_pb2.py
delta_spark-4.0.0.dist-info/LICENSE.txt
delta_spark-4.0.0.dist-info/METADATA
delta_spark-4.0.0.dist-info/NOTICE.txt
delta_spark-4.0.0.dist-info/WHEEL
delta_spark-4.0.0.dist-info/top_level.txt
delta_spark-4.0.0.dist-info/RECORD
