Metadata-Version: 2.1
Name: delta-spark
Version: 4.0.0
Summary: Python APIs for using Delta Lake with Apache Spark
Home-page: https://github.com/delta-io/delta/
Author: The Delta Lake Project Authors
Author-email: delta-users@googlegroups.com
License: Apache-2.0
Project-URL: Source, https://github.com/delta-io/delta
Project-URL: Documentation, https://docs.delta.io/latest/index.html
Project-URL: Issues, https://github.com/delta-io/delta/issues
Keywords: delta.io
Platform: UNKNOWN
Classifier: Development Status :: 5 - Production/Stable
Classifier: Intended Audience :: Developers
Classifier: License :: OSI Approved :: Apache Software License
Classifier: Operating System :: OS Independent
Classifier: Topic :: Software Development :: Libraries :: Python Modules
Classifier: Programming Language :: Python :: 3
Classifier: Typing :: Typed
Requires-Python: >=3.9
License-File: LICENSE.txt
License-File: NOTICE.txt
